[
    {
        "key": "dbln",
        "value": "%7B%2261558236585807%22%3A%22Z4daLKyO%22%2C%2261566115512123%22%3A%22YKtMKmAi%22%7D",
        "domain": "facebook.com",
        "path": "/login/device-based/",
        "hostOnly": false,
        "creation": "2024-10-03T16:44:14.025Z",
        "lastAccessed": "2024-10-03T16:44:14.026Z"
    },
    {
        "key": "datr",
        "value": "TwL4ZqcS5bdddPMMmigDowTt",
        "domain": "facebook.com",
        "path": "/",
        "hostOnly": false,
        "creation": "2024-10-03T16:44:14.026Z",
        "lastAccessed": "2024-10-03T16:44:14.026Z"
    },
    {
        "key": "sb",
        "value": "TwL4ZimK3L8ih_ERXXxVhUNT",
        "domain": "facebook.com",
        "path": "/",
        "hostOnly": false,
        "creation": "2024-10-03T16:44:14.026Z",
        "lastAccessed": "2024-10-03T16:44:14.026Z"
    },
    {
        "key": "ps_l",
        "value": "1",
        "domain": "facebook.com",
        "path": "/",
        "hostOnly": false,
        "creation": "2024-10-03T16:44:14.026Z",
        "lastAccessed": "2024-10-03T16:44:14.026Z"
    },
    {
        "key": "ps_n",
        "value": "1",
        "domain": "facebook.com",
        "path": "/",
        "hostOnly": false,
        "creation": "2024-10-03T16:44:14.026Z",
        "lastAccessed": "2024-10-03T16:44:14.026Z"
    },
    {
        "key": "dpr",
        "value": "2.278899669647217",
        "domain": "facebook.com",
        "path": "/",
        "hostOnly": false,
        "creation": "2024-10-03T16:44:14.026Z",
        "lastAccessed": "2024-10-03T16:44:14.026Z"
    },
    {
        "key": "vpd",
        "value": "v1%3B902x480x2.06899356842041",
        "domain": "facebook.com",
        "path": "/",
        "hostOnly": false,
        "creation": "2024-10-03T16:44:14.026Z",
        "lastAccessed": "2024-10-03T16:44:14.026Z"
    },
    {
        "key": "locale",
        "value": "en_GB",
        "domain": "facebook.com",
        "path": "/",
        "hostOnly": false,
        "creation": "2024-10-03T16:44:14.026Z",
        "lastAccessed": "2024-10-03T16:44:14.026Z"
    },
    {
        "key": "m_pixel_ratio",
        "value": "2.06899356842041",
        "domain": "facebook.com",
        "path": "/",
        "hostOnly": false,
        "creation": "2024-10-03T16:44:14.026Z",
        "lastAccessed": "2024-10-03T16:44:14.026Z"
    },
    {
        "key": "c_user",
        "value": "61566115512123",
        "domain": "facebook.com",
        "path": "/",
        "hostOnly": false,
        "creation": "2024-10-03T16:44:14.026Z",
        "lastAccessed": "2024-10-03T16:44:14.026Z"
    },
    {
        "key": "fr",
        "value": "0X2aEagzrhNe5Gd9o.AWUYHzTSSydjuQh__Xd5C_BJ9Mw.Bm-AJP..AAA.0.0.Bm_snO.AWU6IBhlgnU",
        "domain": "facebook.com",
        "path": "/",
        "hostOnly": false,
        "creation": "2024-10-03T16:44:14.026Z",
        "lastAccessed": "2024-10-03T16:44:14.026Z"
    },
    {
        "key": "xs",
        "value": "31%3AQfWHkyN41fLNCg%3A2%3A1727973838%3A-1%3A11284",
        "domain": "facebook.com",
        "path": "/",
        "hostOnly": false,
        "creation": "2024-10-03T16:44:14.026Z",
        "lastAccessed": "2024-10-03T16:44:14.026Z"
    },
    {
        "key": "m_page_voice",
        "value": "61566115512123",
        "domain": "facebook.com",
        "path": "/",
        "hostOnly": false,
        "creation": "2024-10-03T16:44:14.026Z",
        "lastAccessed": "2024-10-03T16:44:14.026Z"
    },
    {
        "key": "wd",
        "value": "522x981",
        "domain": "facebook.com",
        "path": "/",
        "hostOnly": false,
        "creation": "2024-10-03T16:44:14.026Z",
        "lastAccessed": "2024-10-03T16:44:14.026Z"
    },
    {
        "key": "fbl_st",
        "value": "100420546%3BT%3A28799564",
        "domain": "facebook.com",
        "path": "/",
        "hostOnly": false,
        "creation": "2024-10-03T16:44:14.026Z",
        "lastAccessed": "2024-10-03T16:44:14.026Z"
    },
    {
        "key": "wl_cbv",
        "value": "v2%3Bclient_version%3A2635%3Btimestamp%3A1727973850",
        "domain": "facebook.com",
        "path": "/",
        "hostOnly": false,
        "creation": "2024-10-03T16:44:14.026Z",
        "lastAccessed": "2024-10-03T16:44:14.026Z"
    }
]
